sensirion_sps30/__init__.py
sensirion_sps30/helper.py
sensirion_sps30/sps30.py
sensirion_sps30-0.2.0.dist-info/LICENSE
sensirion_sps30-0.2.0.dist-info/WHEEL
sensirion_sps30-0.2.0.dist-info/METADATA
sensirion_sps30-0.2.0.dist-info/RECORD
