Metadata-Version: 2.1
Name: sensirion-sps30
Version: 0.2.0
Summary: Sensirion SPS30 Python library
Home-page: https://github.com/MMartin09/sensirion-sps30
License: MIT
Author: MMartin09
Author-email: mmartin09@outlook.at
Requires-Python: >=3.6.1,<4.0.0
Classifier: Development Status :: 4 - Beta
Classifier: Intended Audience :: Science/Research
Classifier: License :: OSI Approved :: MIT License
Classifier: Natural Language :: English
Classifier: Operating System :: OS Independent
Classifier: Programming Language :: Python :: 3
Classifier: Programming Language :: Python :: 3 :: Only
Classifier: Programming Language :: Python :: 3.10
Classifier: Programming Language :: Python :: 3.6
Classifier: Programming Language :: Python :: 3.7
Classifier: Programming Language :: Python :: 3.8
Classifier: Programming Language :: Python :: 3.9
Classifier: Topic :: Scientific/Engineering :: Atmospheric Science
Classifier: Topic :: Terminals :: Serial
Requires-Dist: pyserial (>=3.5,<4.0)
Project-URL: Repository, https://github.com/MMartin09/sensirion-sps30
